COPYING
LICENSE
MANIFEST.in
README.rst
setup.py
django_pushserver.egg-info/PKG-INFO
django_pushserver.egg-info/SOURCES.txt
django_pushserver.egg-info/dependency_links.txt
django_pushserver.egg-info/not-zip-safe
django_pushserver.egg-info/requires.txt
django_pushserver.egg-info/top_level.txt
docs/Makefile
docs/conf.py
docs/index.rst
docs/installation.rst
docs/usage.rst
pushserver/__init__.py
pushserver/models.py
pushserver/signals.py
pushserver/tests.py
pushserver/urls.py
pushserver/views.py
pushserver/management/__init__.py
pushserver/management/commands/__init__.py
pushserver/management/commands/runpushserver.py
pushserver/static/pushserver/updates.js
pushserver/templatetags/__init__.py
pushserver/templatetags/pushserver.py
pushserver/utils/__init__.py
pushserver/utils/updates.py
pushserver/utils/urllib.py